lazyfile/__init__.py
lazyfile/lazyfile.py
lazyfile/sparsebytes.py
lazyfile-0.1.dist-info/LICENSE
lazyfile-0.1.dist-info/METADATA
lazyfile-0.1.dist-info/WHEEL
lazyfile-0.1.dist-info/top_level.txt
lazyfile-0.1.dist-info/RECORD
