Metadata-Version: 2.1
Name: lazyfile
Version: 0.1
Summary: Lazy-loaded file objects
Home-page: https://github.com/pfmoore/lazyfile
Author: Paul Moore
Author-email: p.f.moore@gmail.com
License: UNKNOWN
Project-URL: Bug Tracker, https://github.com/pfmoore/lazyfile/issues
Platform: UNKNOWN
Classifier: Programming Language :: Python :: 3
Classifier: License :: OSI Approved :: MIT License
Classifier: Operating System :: OS Independent
Requires-Python: >=3.6
License-File: LICENSE
Requires-Dist: spans
